app/__init__.py
app/app.py
app/celery/__init__.py
app/cli/__init__.py
app/cli/celery.py
app/cli/db.py
app/cli/users.py
app/database.py
app/mail/__init__.py
app/main.py
app/models/orm/__init__.py
app/models/orm/base.py
app/models/orm/category.py
app/models/orm/connection.py
app/models/orm/discovery.py
app/models/orm/plan.py
app/models/orm/plan_instance.py
app/models/orm/rule.py
app/models/orm/setting.py
app/models/orm/user.py
app/models/schemas/__init__.py
app/models/schemas/app_settings.py
app/models/schemas/application.py
app/models/schemas/auth.py
app/models/schemas/base.py
app/models/schemas/category.py
app/models/schemas/connection.py
app/models/schemas/discovery/__init__.py
app/models/schemas/discovery/base.py
app/models/schemas/discovery/discovery.py
app/models/schemas/discovery/plan.py
app/models/schemas/discovery/plan_instance.py
app/models/schemas/discovery/rule.py
app/models/schemas/metadata.py
app/models/schemas/mssql/__init__.py
app/models/schemas/notification.py
app/models/schemas/oracle/redact/__init__.py
app/models/schemas/oracle/redact/base.py
app/models/schemas/oracle/redact/column.py
app/models/schemas/oracle/redact/expression.py
app/models/schemas/oracle/redact/function.py
app/models/schemas/oracle/redact/policy.py
app/models/schemas/oracle/redact/redact.py
app/models/schemas/settings.py
app/models/schemas/user.py
app/redis/__init__.py
app/routes/__init__.py
app/routes/app_settings.py
app/routes/application.py
app/routes/auth.py
app/routes/base.py
app/routes/categories.py
app/routes/connections.py
app/routes/discovery/__init__.py
app/routes/discovery/base.py
app/routes/discovery/discoveries.py
app/routes/discovery/plan_instances.py
app/routes/discovery/plans.py
app/routes/discovery/rules.py
app/routes/metadata.py
app/routes/mssql/__init__.py
app/routes/mssql/base.py
app/routes/mssql/masks.py
app/routes/notifications.py
app/routes/oracle/__init__.py
app/routes/oracle/redact/__init__.py
app/routes/oracle/redact/base.py
dbredact-0.5.15.dist-info/entry_points.txt
dbredact-0.5.15.dist-info/WHEEL
dbredact-0.5.15.dist-info/METADATA
dbredact-0.5.15.dist-info/RECORD
