Metadata-Version: 2.1
Name: dbredact
Version: 0.5.15
Summary: Data Redaction Application
Home-page: https://github.com/bluecolor/redact
License: CC BY-NC-SA 4.0
Keywords: redaction,masking
Author: Ceyhun Kerti
Author-email: ceyhun.kerti@bluecolor.io
Requires-Python: >=3.8,<4.0
Classifier: License :: Other/Proprietary License
Classifier: Programming Language :: Python :: 3
Classifier: Programming Language :: Python :: 3.8
Classifier: Programming Language :: Python :: 3.9
Requires-Dist: Jinja2 (>=2.11.3,<3.0.0)
Requires-Dist: aiofiles (>=0.6.0,<0.7.0)
Requires-Dist: aioredis (>=1.3.1,<2.0.0)
Requires-Dist: alembic (>=1.4.2,<2.0.0)
Requires-Dist: arq (>=0.19,<0.20)
Requires-Dist: async-timeout (>=3.0.1,<4.0.0)
Requires-Dist: celery (>=5.0.5,<6.0.0)
Requires-Dist: click (>=7.1.2,<8.0.0)
Requires-Dist: cryptography (>=3.4.4,<4.0.0)
Requires-Dist: cx-Oracle (>=8.1.0,<9.0.0)
Requires-Dist: email_validator (>=1.1.0,<2.0.0)
Requires-Dist: fastapi (>=0.63.0,<0.64.0)
Requires-Dist: fastapi-mail (>=0.3.5,<0.4.0)
Requires-Dist: fastapi-pagination (>=0.6.1,<0.7.0)
Requires-Dist: keyrings.alt (>=4.0.2,<5.0.0)
Requires-Dist: mkdocs-material (>=7.0.6,<8.0.0)
Requires-Dist: passlib (>=1.7.4,<2.0.0)
Requires-Dist: psycopg2-binary (>=2.8.5,<3.0.0)
Requires-Dist: pydash (>=4.9.3,<5.0.0)
Requires-Dist: pymssql (>=2.2.0,<3.0.0)
Requires-Dist: python-jose (>=3.2.0,<4.0.0)
Requires-Dist: python-multipart (>=0.0.5,<0.0.6)
Requires-Dist: redis (>=3.5.3,<4.0.0)
Requires-Dist: sentry-sdk (>=0.14.3,<0.15.0)
Requires-Dist: sqlalchemy-utils (>=0.36.5,<0.37.0)
Requires-Dist: starlette-context (>=0.3.1,<0.4.0)
Requires-Dist: uvicorn (>=0.11.5,<0.12.0)
Project-URL: Documentation, https://bluecolor.github.io/redact/
Project-URL: Repository, https://github.com/bluecolor/redact
